MANIFEST.in
README.txt
setup.cfg
setup.py
adi/__init__.py
adi.ttw_styles.egg-info/PKG-INFO
adi.ttw_styles.egg-info/SOURCES.txt
adi.ttw_styles.egg-info/dependency_links.txt
adi.ttw_styles.egg-info/entry_points.txt
adi.ttw_styles.egg-info/namespace_packages.txt
adi.ttw_styles.egg-info/not-zip-safe
adi.ttw_styles.egg-info/paster_plugins.txt
adi.ttw_styles.egg-info/requires.txt
adi.ttw_styles.egg-info/top_level.txt
adi/ttw_styles/__init__.py
adi/ttw_styles/configure.zcml
adi/ttw_styles/tests.py
adi/ttw_styles/ttw_styles_view.pt
adi/ttw_styles/profiles/default/cssregistry.xml
adi/ttw_styles/profiles/default/metadata.xml