Metadata-Version: 1.1
Name: adi.ttw-styles
Version: 1.1
Summary: Apply your styles TTW.
Home-page: http://svn.plone.org/svn/collective/
Author: Ida Ebkes
Author-email: contact@ida-ebkes.eu
License: GPL
Platform: UNKNOWN
Classifier: Framework :: Plone
Classifier: Programming Language :: Python
